LICENSE
MANIFEST.in
README.md
requirements.txt
setup.py
diplomat/__init__.py
diplomat/admin.py
diplomat/fields.py
diplomat/models.py
diplomat/tests.py
diplomat/fixtures/initial_data.json
diplomat/management/__init__.py
diplomat/management/commands/__init__.py
diplomat/management/commands/diplomat_sync.py
django_diplomat.egg-info/PKG-INFO
django_diplomat.egg-info/SOURCES.txt
django_diplomat.egg-info/dependency_links.txt
django_diplomat.egg-info/not-zip-safe
django_diplomat.egg-info/requires.txt
django_diplomat.egg-info/top_level.txt