Metadata-Version: 1.0
Name: django-diplomat
Version: 0.2.0
Summary: Language and country models for Django derived from the pycountry module.
Home-page: http://github.com/oberlin/django-diplomat/
Author: Justin Locsei
Author-email: justin.locsei@oberlin.edu
License: BSD
Download-URL: https://github.com/oberlin/django-diplomat/zipball/master
Platform: any
Classifier: Development Status :: 3 - Alpha
Classifier: Environment :: Web Environment
Classifier: Framework :: Django
Classifier: Intended Audience :: Developers
Classifier: License :: OSI Approved :: BSD License
Classifier: Operating System :: OS Independent
Classifier: Programming Language :: Python
Classifier: Topic :: Software Development :: Libraries :: Python Modules
